spotifyyy_dl/__init__.py
spotifyyy_dl/download.py
spotifyyy_dl/enum.py
spotifyyy_dl/model.py
spotifyyy_dl/printf.py
spotifyyy_dl/settings.py
spotifyyy_dl/spotify.py
spotifyyy_dl/lang/__init__.py
spotifyyy_dl/lang/arabic.py
spotifyyy_dl/lang/chinese.py
spotifyyy_dl/lang/croatian.py
spotifyyy_dl/lang/czech.py
spotifyyy_dl/lang/english.py
spotifyyy_dl/lang/filipino.py
spotifyyy_dl/lang/french.py
spotifyyy_dl/lang/german.py
spotifyyy_dl/lang/italian.py
spotifyyy_dl/lang/language.py
spotifyyy_dl/lang/portuguese.py
spotifyyy_dl/lang/russian.py
spotifyyy_dl/lang/spanish.py
spotifyyy_dl/lang/turkish.py
spotifyyy_dl/lang/ukrainian.py
spotifyyy_dl/lang/vietnamese.py
spotifyyy_dl-2021.5.25.0.dist-info/METADATA
spotifyyy_dl-2021.5.25.0.dist-info/WHEEL
spotifyyy_dl-2021.5.25.0.dist-info/entry_points.txt
spotifyyy_dl-2021.5.25.0.dist-info/top_level.txt
spotifyyy_dl-2021.5.25.0.dist-info/RECORD
