Metadata-Version: 2.1
Name: spotifyyy-dl
Version: 2021.5.25.0
Summary: Spotify Music Downloader.
Home-page: UNKNOWN
Author: YaronH
Author-email: yaronhuang@foxmail.com
License: Apache2
Platform: any
Requires-Dist: aigpy (>=2021.3.25.2)
Requires-Dist: requests (>=2.22.0)
Requires-Dist: pycryptodome
Requires-Dist: pydub
Requires-Dist: prettytable
Requires-Dist: spotipy
Requires-Dist: ytmusicapi
Requires-Dist: pytube
